eastnine_demo1/__init__.py
eastnine_demo1/__main__.py
eastnine_demo1-1.0.0.dist-info/METADATA
eastnine_demo1-1.0.0.dist-info/WHEEL
eastnine_demo1-1.0.0.dist-info/entry_points.txt
eastnine_demo1-1.0.0.dist-info/RECORD
